pylizai/__init__.py
pylizai/core/__init__.py
pylizai/core/ai_models.py
pylizai/core/ai_pyliz.py
pylizai/core/ai_results.py
pylizai/core/ai_setting.py
pylizai/core/ai_source.py
pylizai/core/ai_source_type.py
pylizai/llm/__init__.py
pylizai/llm/gemini.py
pylizai/llm/llama_cpp.py
pylizai/llm/lmstudio.py
pylizai/llm/mistral.py
pylizai/llm/ollamaliz.py
pylizai/llm/whisper.py
pylizai/log/__init__.py
pylizai/log/pylizAiLogging.py
pylizai/media/__init__.py
pylizai/media/ai_image_scanner.py
pylizai/media/ai_media_scanner.py
pylizai/media/ai_video_scanner.py
pylizai/media/liz_media_exp.py
pylizai/model/__init__.py
pylizai/model/ai_dw_type.py
pylizai/model/ai_env.py
pylizai/model/ai_exctps.py
pylizai/model/ai_file_type.py
pylizai/model/ai_model_list.py
pylizai/model/ai_power.py
pylizai/model/ai_prompts.py
pylizai/model/ai_runner_log.py
pylizai/model/ai_scan_settings.py
pylizai/old/__init__.py
pylizai/old/customPrompt.py
pylizai/old/llava.py
pylizai/old/ollama_models.py
pylizai/old/ollama_response.py
pylizai/old/whisper.py
pylizai/runner/__init__.py
pylizai/runner/ai_common_runner.py
pylizai/runner/ai_runner.py
pylizai/utils/__init__.py
pylizai/utils/ai_chkr.py
pylizai/utils/ai_dwder.py
pylizai/utils/ai_msg_gen.py
pylizai/utils/ai_res_extr.py
test/__init__.py
test/pylizAiTest.py
test/test_ai_image.py
test/test_gemini.py
test/test_general.py
test/test_llamacpp.py
test/test_llamacpp_lib.py
test/test_lmstudio.py
test/test_mistral.py
test/test_ollama.py
test/test_runnerScheduler.py
test/test_scanner.py
test/test_whisper.py
pyliz_ai-0.2.12.dist-info/METADATA
pyliz_ai-0.2.12.dist-info/WHEEL
pyliz_ai-0.2.12.dist-info/top_level.txt
pyliz_ai-0.2.12.dist-info/RECORD
