Metadata-Version: 2.2
Name: pyliz-ai
Version: 0.2.12
Summary: Library to interact with local/remote LLM.
Author: Gabliz
Author-email: 
Keywords: python,video,ai,utilities
Classifier: Development Status :: 1 - Planning
Classifier: Intended Audience :: Developers
Classifier: Programming Language :: Python :: 3
Classifier: Operating System :: Unix
Classifier: Operating System :: MacOS :: MacOS X
Classifier: Operating System :: Microsoft :: Windows
Requires-Dist: pylizlib
Requires-Dist: pylizmedia
Requires-Dist: google-generativeai
Requires-Dist: mistralai
Requires-Dist: ollama
Requires-Dist: openai-whisper
Requires-Dist: librosa
Requires-Dist: torch
Requires-Dist: huggingface-hub
Requires-Dist: transformers==4.46.2
Requires-Dist: eagleliz
Dynamic: author
Dynamic: classifier
Dynamic: description
Dynamic: description-content-type
Dynamic: keywords
Dynamic: requires-dist
Dynamic: summary
